__init__.py
fibep_interpreter.py
fibep_validator.py
fibepjson-0.2.dist-info/LICENSE
fibepjson-0.2.dist-info/METADATA
fibepjson-0.2.dist-info/WHEEL
fibepjson-0.2.dist-info/top_level.txt
fibepjson-0.2.dist-info/RECORD
