Metadata-Version: 2.1
Name: fibepjson
Version: 0.2
Summary: Package to encode and decode JSON files with the standard exchange format of the Federation International de Bureaux d'Extraits de Presse.
Author-email: Carlos Alfredo Diaz <yo@carlosdiaz.com.ar>
Project-URL: Homepage, https://dataexchange.fibep.info/
Project-URL: Bug Tracker, https://github.com/arankwende/FIBEP-JSON-Interpreter
Classifier: Programming Language :: Python :: 3
Classifier: License :: OSI Approved :: MIT License
Classifier: Operating System :: OS Independent
Requires-Python: >=3.9
License-File: LICENSE
